byu_accounting/__init__.py
byu_accounting/byu_accounting.py
byu_accounting-0.1.17.dist-info/licenses/LICENSE
byu_accounting-0.1.17.dist-info/METADATA
byu_accounting-0.1.17.dist-info/WHEEL
byu_accounting-0.1.17.dist-info/top_level.txt
byu_accounting-0.1.17.dist-info/RECORD
