Metadata-Version: 2.4
Name: byu_accounting
Version: 0.1.17
Summary: Package for use by BYU Accounting Students
Home-page: https://github.com/joshlee84/byu_accounting
Author: Josh Lee
Author-email: joshlee84@byu.edu
License: MIT
Classifier: Development Status :: 3 - Alpha
Classifier: Intended Audience :: Education
Classifier: License :: OSI Approved :: MIT License
Classifier: Operating System :: OS Independent
Classifier: Programming Language :: Python :: 3
Classifier: Programming Language :: Python :: 3.7
Classifier: Programming Language :: Python :: 3.8
Classifier: Programming Language :: Python :: 3.9
Classifier: Programming Language :: Python :: 3.10
Requires-Python: >=3.7
License-File: LICENSE
Requires-Dist: requests
Requires-Dist: pypdf
Requires-Dist: pandas
Requires-Dist: selenium
Requires-Dist: tk
Requires-Dist: numpy
Dynamic: author
Dynamic: author-email
Dynamic: classifier
Dynamic: description
Dynamic: description-content-type
Dynamic: home-page
Dynamic: license
Dynamic: license-file
Dynamic: requires-dist
Dynamic: requires-python
Dynamic: summary
